README.md
setup.py
trelliopg/__init__.py
trelliopg/sql.py
trelliopg.egg-info/PKG-INFO
trelliopg.egg-info/SOURCES.txt
trelliopg.egg-info/dependency_links.txt
trelliopg.egg-info/requires.txt
trelliopg.egg-info/top_level.txt