Metadata-Version: 1.0
Name: trelliopg
Version: 0.0.23
Summary: A fast database connector and micro-orm for postgresql
Home-page: https://github.com/technomaniac/trelliopg
Author: Abhishek Verma, Nirmal Singh
Author-email: ashuverma1989@gmail.com, nirmal.singh.cer08@itbhu.ac.in
License: UNKNOWN
Platform: UNKNOWN
